[
 {
  "allow_in_quick_entry": 0,
  "allow_on_submit": 0,
  "bold": 0,
  "collapsible": 0,
  "collapsible_depends_on": null,
  "columns": 0,
  "default": null,
  "depends_on": null,
  "description": null,
  "docstatus": 0,
  "doctype": "Custom Field",
  "dt": "Property Unit",
  "fetch_from": null,
  "fetch_if_empty": 0,
  "fieldname": "column_break_5",
  "fieldtype": "Column Break",
  "hidden": 0,
  "hide_border": 0,
  "hide_days": 0,
  "hide_seconds": 0,
  "ignore_user_permissions": 0,
  "ignore_xss_filter": 0,
  "in_global_search": 0,
  "in_list_view": 0,
  "in_preview": 0,
  "in_standard_filter": 0,
  "insert_after": "unit_status",
  "label": null,
  "length": 0,
  "mandatory_depends_on": null,
  "modified": "2022-02-18 15:55:55.138032",
  "name": "Property Unit-column_break_5",
  "no_copy": 0,
  "non_negative": 0,
  "options": null,
  "parent": null,
  "parentfield": null,
  "parenttype": null,
  "permlevel": 0,
  "precision": "",
  "print_hide": 0,
  "print_hide_if_no_value": 0,
  "print_width": null,
  "read_only": 0,
  "read_only_depends_on": null,
  "report_hide": 0,
  "reqd": 0,
  "search_index": 0,
  "translatable": 0,
  "unique": 0,
  "width": null
 },
 {
  "allow_in_quick_entry": 0,
  "allow_on_submit": 0,
  "bold": 0,
  "collapsible": 1,
  "collapsible_depends_on": null,
  "columns": 0,
  "default": null,
  "depends_on": "eval:doc.company=='ABU DHABI POULTRY FARM - SOLE PROPRIETORSHIP L.L.C.'",
  "description": null,
  "docstatus": 0,
  "doctype": "Custom Field",
  "dt": "Sales Invoice",
  "fetch_from": null,
  "fetch_if_empty": 0,
  "fieldname": "property_unit_details",
  "fieldtype": "Section Break",
  "hidden": 0,
  "hide_border": 0,
  "hide_days": 0,
  "hide_seconds": 0,
  "ignore_user_permissions": 0,
  "ignore_xss_filter": 0,
  "in_global_search": 0,
  "in_list_view": 0,
  "in_preview": 0,
  "in_standard_filter": 0,
  "insert_after": "set_target_warehouse",
  "label": "Property Details",
  "length": 0,
  "mandatory_depends_on": null,
  "modified": "2022-02-18 15:58:10.854347",
  "name": "Sales Invoice-property_unit_details",
  "no_copy": 0,
  "non_negative": 0,
  "options": null,
  "parent": null,
  "parentfield": null,
  "parenttype": null,
  "permlevel": 0,
  "precision": "",
  "print_hide": 0,
  "print_hide_if_no_value": 0,
  "print_width": null,
  "read_only": 0,
  "read_only_depends_on": null,
  "report_hide": 0,
  "reqd": 0,
  "search_index": 0,
  "translatable": 0,
  "unique": 0,
  "width": null
 },
 {
  "allow_in_quick_entry": 0,
  "allow_on_submit": 0,
  "bold": 0,
  "collapsible": 0,
  "collapsible_depends_on": null,
  "columns": 0,
  "default": null,
  "depends_on": null,
  "description": null,
  "docstatus": 0,
  "doctype": "Custom Field",
  "dt": "Sales Invoice",
  "fetch_from": null,
  "fetch_if_empty": 0,
  "fieldname": "property",
  "fieldtype": "Link",
  "hidden": 0,
  "hide_border": 0,
  "hide_days": 0,
  "hide_seconds": 0,
  "ignore_user_permissions": 0,
  "ignore_xss_filter": 0,
  "in_global_search": 0,
  "in_list_view": 0,
  "in_preview": 0,
  "in_standard_filter": 0,
  "insert_after": "property_unit_details",
  "label": "Property",
  "length": 0,
  "mandatory_depends_on": null,
  "modified": "2022-02-20 11:15:03.782612",
  "name": "Sales Invoice-property",
  "no_copy": 0,
  "non_negative": 0,
  "options": "Property Master",
  "parent": null,
  "parentfield": null,
  "parenttype": null,
  "permlevel": 0,
  "precision": "",
  "print_hide": 0,
  "print_hide_if_no_value": 0,
  "print_width": null,
  "read_only": 0,
  "read_only_depends_on": null,
  "report_hide": 0,
  "reqd": 0,
  "search_index": 0,
  "translatable": 0,
  "unique": 0,
  "width": null
 },
 {
  "allow_in_quick_entry": 0,
  "allow_on_submit": 0,
  "bold": 0,
  "collapsible": 0,
  "collapsible_depends_on": null,
  "columns": 0,
  "default": null,
  "depends_on": "eval:doc.property",
  "description": null,
  "docstatus": 0,
  "doctype": "Custom Field",
  "dt": "Sales Invoice",
  "fetch_from": null,
  "fetch_if_empty": 0,
  "fieldname": "property_unit",
  "fieldtype": "Link",
  "hidden": 0,
  "hide_border": 0,
  "hide_days": 0,
  "hide_seconds": 0,
  "ignore_user_permissions": 0,
  "ignore_xss_filter": 0,
  "in_global_search": 0,
  "in_list_view": 0,
  "in_preview": 0,
  "in_standard_filter": 0,
  "insert_after": "property",
  "label": "Property Unit",
  "length": 0,
  "mandatory_depends_on": null,
  "modified": "2022-02-20 11:35:16.720714",
  "name": "Sales Invoice-property_unit",
  "no_copy": 0,
  "non_negative": 0,
  "options": "Property Unit",
  "parent": null,
  "parentfield": null,
  "parenttype": null,
  "permlevel": 0,
  "precision": "",
  "print_hide": 0,
  "print_hide_if_no_value": 0,
  "print_width": null,
  "read_only": 0,
  "read_only_depends_on": null,
  "report_hide": 0,
  "reqd": 0,
  "search_index": 0,
  "translatable": 0,
  "unique": 0,
  "width": null
 },
 {
  "allow_in_quick_entry": 0,
  "allow_on_submit": 0,
  "bold": 0,
  "collapsible": 0,
  "collapsible_depends_on": null,
  "columns": 0,
  "default": null,
  "depends_on": null,
  "description": null,
  "docstatus": 0,
  "doctype": "Custom Field",
  "dt": "Sales Invoice",
  "fetch_from": null,
  "fetch_if_empty": 0,
  "fieldname": "column_break_64",
  "fieldtype": "Column Break",
  "hidden": 0,
  "hide_border": 0,
  "hide_days": 0,
  "hide_seconds": 0,
  "ignore_user_permissions": 0,
  "ignore_xss_filter": 0,
  "in_global_search": 0,
  "in_list_view": 0,
  "in_preview": 0,
  "in_standard_filter": 0,
  "insert_after": "property_unit",
  "label": null,
  "length": 0,
  "mandatory_depends_on": null,
  "modified": "2022-02-16 14:45:52.528453",
  "name": "Sales Invoice-column_break_64",
  "no_copy": 0,
  "non_negative": 0,
  "options": null,
  "parent": null,
  "parentfield": null,
  "parenttype": null,
  "permlevel": 0,
  "precision": "",
  "print_hide": 0,
  "print_hide_if_no_value": 0,
  "print_width": null,
  "read_only": 0,
  "read_only_depends_on": null,
  "report_hide": 0,
  "reqd": 0,
  "search_index": 0,
  "translatable": 0,
  "unique": 0,
  "width": null
 },
 {
  "allow_in_quick_entry": 0,
  "allow_on_submit": 0,
  "bold": 0,
  "collapsible": 0,
  "collapsible_depends_on": null,
  "columns": 0,
  "default": null,
  "depends_on": null,
  "description": null,
  "docstatus": 0,
  "doctype": "Custom Field",
  "dt": "Sales Invoice",
  "fetch_from": null,
  "fetch_if_empty": 0,
  "fieldname": "contract_start_date",
  "fieldtype": "Date",
  "hidden": 0,
  "hide_border": 0,
  "hide_days": 0,
  "hide_seconds": 0,
  "ignore_user_permissions": 0,
  "ignore_xss_filter": 0,
  "in_global_search": 0,
  "in_list_view": 0,
  "in_preview": 0,
  "in_standard_filter": 0,
  "insert_after": "column_break_64",
  "label": "Contract Start Date",
  "length": 0,
  "mandatory_depends_on": null,
  "modified": "2022-02-16 14:16:53.875158",
  "name": "Sales Invoice-contract_start_date",
  "no_copy": 0,
  "non_negative": 0,
  "options": null,
  "parent": null,
  "parentfield": null,
  "parenttype": null,
  "permlevel": 0,
  "precision": "",
  "print_hide": 0,
  "print_hide_if_no_value": 0,
  "print_width": null,
  "read_only": 0,
  "read_only_depends_on": null,
  "report_hide": 0,
  "reqd": 0,
  "search_index": 0,
  "translatable": 0,
  "unique": 0,
  "width": null
 },
 {
  "allow_in_quick_entry": 0,
  "allow_on_submit": 0,
  "bold": 0,
  "collapsible": 0,
  "collapsible_depends_on": null,
  "columns": 0,
  "default": null,
  "depends_on": null,
  "description": null,
  "docstatus": 0,
  "doctype": "Custom Field",
  "dt": "Sales Invoice",
  "fetch_from": null,
  "fetch_if_empty": 0,
  "fieldname": "contract_end_date",
  "fieldtype": "Date",
  "hidden": 0,
  "hide_border": 0,
  "hide_days": 0,
  "hide_seconds": 0,
  "ignore_user_permissions": 0,
  "ignore_xss_filter": 0,
  "in_global_search": 0,
  "in_list_view": 0,
  "in_preview": 0,
  "in_standard_filter": 0,
  "insert_after": "contract_start_date",
  "label": "Contract End Date",
  "length": 0,
  "mandatory_depends_on": null,
  "modified": "2022-02-16 14:17:53.530713",
  "name": "Sales Invoice-contract_end_date",
  "no_copy": 0,
  "non_negative": 0,
  "options": null,
  "parent": null,
  "parentfield": null,
  "parenttype": null,
  "permlevel": 0,
  "precision": "",
  "print_hide": 0,
  "print_hide_if_no_value": 0,
  "print_width": null,
  "read_only": 0,
  "read_only_depends_on": null,
  "report_hide": 0,
  "reqd": 0,
  "search_index": 0,
  "translatable": 0,
  "unique": 0,
  "width": null
 }
]